aioredis_cluster/__init__.py
aioredis_cluster/_version.py
aioredis_cluster/abc.py
aioredis_cluster/cluster.py
aioredis_cluster/cluster_state.py
aioredis_cluster/command_exec.py
aioredis_cluster/connection.py
aioredis_cluster/crc.py
aioredis_cluster/errors.py
aioredis_cluster/errors.pyi
aioredis_cluster/factory.py
aioredis_cluster/log.py
aioredis_cluster/manager.py
aioredis_cluster/pool.py
aioredis_cluster/pooler.py
aioredis_cluster/pubsub.py
aioredis_cluster/py.typed
aioredis_cluster/resource_lock.py
aioredis_cluster/structs.py
aioredis_cluster/typedef.py
aioredis_cluster/util.py
aioredis_cluster/_aioredis/LICENSE
aioredis_cluster/_aioredis/__init__.py
aioredis_cluster/_aioredis/abc.py
aioredis_cluster/_aioredis/connection.py
aioredis_cluster/_aioredis/errors.py
aioredis_cluster/_aioredis/log.py
aioredis_cluster/_aioredis/parser.py
aioredis_cluster/_aioredis/pool.py
aioredis_cluster/_aioredis/pubsub.py
aioredis_cluster/_aioredis/stream.py
aioredis_cluster/_aioredis/util.py
aioredis_cluster/_aioredis/commands/__init__.py
aioredis_cluster/_aioredis/commands/cluster.py
aioredis_cluster/_aioredis/commands/generic.py
aioredis_cluster/_aioredis/commands/geo.py
aioredis_cluster/_aioredis/commands/hash.py
aioredis_cluster/_aioredis/commands/hyperloglog.py
aioredis_cluster/_aioredis/commands/list.py
aioredis_cluster/_aioredis/commands/pubsub.py
aioredis_cluster/_aioredis/commands/scripting.py
aioredis_cluster/_aioredis/commands/server.py
aioredis_cluster/_aioredis/commands/set.py
aioredis_cluster/_aioredis/commands/sorted_set.py
aioredis_cluster/_aioredis/commands/streams.py
aioredis_cluster/_aioredis/commands/string.py
aioredis_cluster/_aioredis/commands/transaction.py
aioredis_cluster/_aioredis/sentinel/__init__.py
aioredis_cluster/_aioredis/sentinel/commands.py
aioredis_cluster/_aioredis/sentinel/pool.py
aioredis_cluster/aioredis/__init__.py
aioredis_cluster/aioredis/abc.py
aioredis_cluster/aioredis/connection.py
aioredis_cluster/aioredis/errors.py
aioredis_cluster-2.7.0.dist-info/LICENSE
aioredis_cluster-2.7.0.dist-info/METADATA
aioredis_cluster-2.7.0.dist-info/WHEEL
aioredis_cluster-2.7.0.dist-info/top_level.txt
aioredis_cluster-2.7.0.dist-info/RECORD
