Metadata-Version: 2.1
Name: aioredis-cluster
Version: 2.7.0
Summary: Redis Cluster support extension for aioredis
Author-email: Anton Ilyushenkov <ilyushenkov@corp.mail.ru>
Maintainer-email: Anton Ilyushenkov <ilyushenkov@corp.mail.ru>
Project-URL: Repository, https://github.com/DriverX/aioredis-cluster
Keywords: redis,aioredis,redis cluster,asyncio
Platform: POSIX
Classifier: License :: OSI Approved :: MIT License
Classifier: Development Status :: 5 - Production/Stable
Classifier: Programming Language :: Python
Classifier: Programming Language :: Python :: 3
Classifier: Programming Language :: Python :: 3.8
Classifier: Programming Language :: Python :: 3.9
Classifier: Programming Language :: Python :: 3.10
Classifier: Programming Language :: Python :: 3.11
Classifier: Programming Language :: Python :: 3.12
Classifier: Programming Language :: Python :: 3 :: Only
Classifier: Operating System :: POSIX
Classifier: Environment :: Web Environment
Classifier: Intended Audience :: Developers
Classifier: Topic :: Software Development
Classifier: Topic :: Software Development :: Libraries
Classifier: Framework :: AsyncIO
Requires-Python: >=3.8
License-File: LICENSE
Requires-Dist: async-timeout; python_version < "3.11"
Requires-Dist: hiredis<3.0.0; platform_python_implementation == "CPython"
Provides-Extra: devel
Requires-Dist: flake8; extra == "devel"
Requires-Dist: flake8-pyproject; extra == "devel"
Requires-Dist: mypy; extra == "devel"
Requires-Dist: isort; extra == "devel"
Requires-Dist: black==23.7.0; extra == "devel"
Requires-Dist: coverage; extra == "devel"
Requires-Dist: cython; extra == "devel"
Requires-Dist: pytest; extra == "devel"
Requires-Dist: pytest-cov; extra == "devel"
Requires-Dist: pytest-mock; extra == "devel"
Requires-Dist: pytest-asyncio<1.0,>=0.21; extra == "devel"
Requires-Dist: pytest-cov; extra == "devel"
Requires-Dist: pytest-xdist; extra == "devel"
Provides-Extra: aioredis
Requires-Dist: aioredis<1.4.0,>=1.1.0; python_version < "3.10" and extra == "aioredis"
